occupy_lib/__init__.py
occupy_lib/_version.py
occupy_lib/args.py
occupy_lib/estimate.py
occupy_lib/extras.py
occupy_lib/map_tools.py
occupy_lib/occupancy.py
occupy_lib/occupy.py
occupy_lib/occupy_gui.py
occupy_lib/percentile_maxima.py
occupy_lib/solvent.py
occupy_lib/vis.py
OccuPy-0.1.13.dist-info/LICENSE
OccuPy-0.1.13.dist-info/METADATA
OccuPy-0.1.13.dist-info/WHEEL
OccuPy-0.1.13.dist-info/entry_points.txt
OccuPy-0.1.13.dist-info/top_level.txt
OccuPy-0.1.13.dist-info/RECORD
