Metadata-Version: 2.1
Name: OccuPy
Version: 0.1.13
Summary: OccuPy: Estimation of local scale in cryo-EM maps
Home-page: https://occupy.readthedocs.io/
Author: Bjoern O. Forsberg
Author-email: bjorn.forsberg@ki.se
License: GPLv3
Project-URL: Source Code, https://github.com/bforsbe/OccuPy
Classifier: Development Status :: 3 - Alpha
Classifier: License :: OSI Approved :: GNU General Public License v3 (GPLv3)
Classifier: Natural Language :: English
Classifier: Programming Language :: Python :: 3
Classifier: Programming Language :: Python :: 3 :: Only
Classifier: Programming Language :: Python :: 3.8
Classifier: Programming Language :: Python :: 3.9
Requires-Python: >=3.8
License-File: LICENSE
Requires-Dist: numpy
Requires-Dist: mrcfile >=1.4.3
Requires-Dist: scipy
Requires-Dist: typer
Requires-Dist: matplotlib
Requires-Dist: scikit-image
Requires-Dist: wget
Provides-Extra: dev
Requires-Dist: black ; extra == 'dev'
Requires-Dist: flake8 ; extra == 'dev'
Requires-Dist: flake8-docstrings ; extra == 'dev'
Requires-Dist: ipython ; extra == 'dev'
Requires-Dist: isort ; extra == 'dev'
Requires-Dist: jedi <0.18.0 ; extra == 'dev'
Requires-Dist: mkdocs ; extra == 'dev'
Requires-Dist: mkdocs-material ; extra == 'dev'
Requires-Dist: mypy ; extra == 'dev'
Requires-Dist: pre-commit ; extra == 'dev'
Requires-Dist: pydocstyle ; extra == 'dev'
Requires-Dist: pytest ; extra == 'dev'
Requires-Dist: pyinstaller ; extra == 'dev'
Provides-Extra: pyqt5
Requires-Dist: pyqt5 ; extra == 'pyqt5'
Provides-Extra: testing
Requires-Dist: pytest ; extra == 'testing'
